wenfire/__init__.py
wenfire/_version.py
wenfire/app.py
wenfire/fire.py
wenfire/plots.py
wenfire/static/README.md
wenfire/static/styles.css
wenfire/static/utils.js
wenfire/templates/index.html.jinja2
wenfire/templates/parameter_change.html.jinja2
wenfire/templates/parameter_row.html.jinja2
wenfire/templates/results_partial.html.jinja2
wenfire-0.2.0.dist-info/METADATA
wenfire-0.2.0.dist-info/WHEEL
wenfire-0.2.0.dist-info/licenses/LICENSE
wenfire-0.2.0.dist-info/RECORD
