Metadata-Version: 2.4
Name: wenfire
Version: 0.2.0
Summary: WenFire 🔥 Financial Independence Calculator 💸
License-File: LICENSE
Requires-Python: >=3.12
Requires-Dist: altair>=5.4.1
Requires-Dist: fastapi-htmx>=0.4.4
Requires-Dist: fastapi[all]>=0.115.0
Requires-Dist: python-dateutil>=2.9.0.post0
Requires-Dist: python-multipart>=0.0.12
